chessboard_generator/__init__.py
chessboard_generator/__main__.py
chessboard_generator/generator.py
opencv_chessboard_generator-1.0.7.dist-info/licenses/LICENSE
opencv_chessboard_generator-1.0.7.dist-info/METADATA
opencv_chessboard_generator-1.0.7.dist-info/WHEEL
opencv_chessboard_generator-1.0.7.dist-info/entry_points.txt
opencv_chessboard_generator-1.0.7.dist-info/top_level.txt
opencv_chessboard_generator-1.0.7.dist-info/RECORD
