Metadata-Version: 2.4
Name: opencv-chessboard-generator
Version: 1.0.7
Summary: A tool to generate chessboard patterns for OpenCV camera calibration
Home-page: https://github.com/flavvesResearch/chessboard-calibration-generator
Author: batuhan ÖKMEN
Author-email: Batuhan ÖKMEN <batuhanokmen@gmail.com>
License: MIT
Project-URL: Homepage, https://github.com/flavvesResearch/chessboard-calibration-generator
Project-URL: Bug Reports, https://github.com/flavvesResearch/chessboard-calibration-generator/issues
Project-URL: Source, https://github.com/flavvesResearch/chessboard-calibration-generator
Keywords: opencv,calibration,chessboard,camera,computer-vision
Classifier: Development Status :: 5 - Production/Stable
Classifier: Intended Audience :: Developers
Classifier: Intended Audience :: Science/Research
Classifier: Topic :: Scientific/Engineering :: Image Recognition
Classifier: License :: OSI Approved :: MIT License
Classifier: Programming Language :: Python :: 3
Classifier: Programming Language :: Python :: 3.7
Classifier: Programming Language :: Python :: 3.8
Classifier: Programming Language :: Python :: 3.9
Classifier: Programming Language :: Python :: 3.10
Classifier: Programming Language :: Python :: 3.11
Requires-Python: >=3.7
License-File: LICENSE
Requires-Dist: opencv-python>=4.5.0
Requires-Dist: numpy>=1.19.0
Dynamic: author
Dynamic: home-page
Dynamic: license-file
Dynamic: requires-python
